{
 "custom_fields": [
  {
   "_assign": null,
   "_comments": null,
   "_liked_by": null,
   "_user_tags": null,
   "allow_in_quick_entry": 0,
   "allow_on_submit": 1,
   "bold": 0,
   "collapsible": 0,
   "collapsible_depends_on": null,
   "columns": 0,
   "creation": "2021-04-26 11:26:50.357969",
   "default": null,
   "depends_on": null,
   "description": null,
   "docstatus": 0,
   "dt": "Quotation Item",
   "fetch_from": "item_code.gst_hsn_code",
   "fetch_if_empty": 1,
   "fieldname": "gst_hsn_code",
   "fieldtype": "Data",
   "hidden": 0,
   "hide_border": 0,
   "hide_days": 0,
   "hide_seconds": 0,
   "idx": 7,
   "ignore_user_permissions": 0,
   "ignore_xss_filter": 0,
   "in_global_search": 0,
   "in_list_view": 0,
   "in_preview": 0,
   "in_standard_filter": 0,
   "insert_after": "description",
   "label": "HSN/SAC",
   "length": 0,
   "mandatory_depends_on": null,
   "modified": "2021-04-26 11:26:50.357969",
   "modified_by": "Administrator",
   "name": "Quotation Item-gst_hsn_code",
   "no_copy": 0,
   "non_negative": 0,
   "options": null,
   "owner": "Administrator",
   "parent": null,
   "parentfield": null,
   "parenttype": null,
   "permlevel": 0,
   "precision": "",
   "print_hide": 1,
   "print_hide_if_no_value": 0,
   "print_width": null,
   "read_only": 0,
   "read_only_depends_on": null,
   "report_hide": 0,
   "reqd": 0,
   "search_index": 0,
   "translatable": 1,
   "unique": 0,
   "width": null
  },
  {
   "_assign": null,
   "_comments": null,
   "_liked_by": null,
   "_user_tags": null,
   "allow_in_quick_entry": 0,
   "allow_on_submit": 0,
   "bold": 0,
   "collapsible": 0,
   "collapsible_depends_on": null,
   "columns": 0,
   "creation": "2021-04-26 11:26:50.506717",
   "default": null,
   "depends_on": null,
   "description": null,
   "docstatus": 0,
   "dt": "Quotation Item",
   "fetch_from": "item_code.is_nil_exempt",
   "fetch_if_empty": 0,
   "fieldname": "is_nil_exempt",
   "fieldtype": "Check",
   "hidden": 0,
   "hide_border": 0,
   "hide_days": 0,
   "hide_seconds": 0,
   "idx": 8,
   "ignore_user_permissions": 0,
   "ignore_xss_filter": 0,
   "in_global_search": 0,
   "in_list_view": 0,
   "in_preview": 0,
   "in_standard_filter": 0,
   "insert_after": "gst_hsn_code",
   "label": "Is Nil Rated or Exempted",
   "length": 0,
   "mandatory_depends_on": null,
   "modified": "2021-04-26 11:26:50.506717",
   "modified_by": "Administrator",
   "name": "Quotation Item-is_nil_exempt",
   "no_copy": 0,
   "non_negative": 0,
   "options": null,
   "owner": "Administrator",
   "parent": null,
   "parentfield": null,
   "parenttype": null,
   "permlevel": 0,
   "precision": "",
   "print_hide": 1,
   "print_hide_if_no_value": 0,
   "print_width": null,
   "read_only": 0,
   "read_only_depends_on": null,
   "report_hide": 0,
   "reqd": 0,
   "search_index": 0,
   "translatable": 0,
   "unique": 0,
   "width": null
  },
  {
   "_assign": null,
   "_comments": null,
   "_liked_by": null,
   "_user_tags": null,
   "allow_in_quick_entry": 0,
   "allow_on_submit": 0,
   "bold": 0,
   "collapsible": 0,
   "collapsible_depends_on": null,
   "columns": 0,
   "creation": "2021-04-26 11:26:50.650860",
   "default": null,
   "depends_on": null,
   "description": null,
   "docstatus": 0,
   "dt": "Quotation Item",
   "fetch_from": "item_code.is_non_gst",
   "fetch_if_empty": 0,
   "fieldname": "is_non_gst",
   "fieldtype": "Check",
   "hidden": 0,
   "hide_border": 0,
   "hide_days": 0,
   "hide_seconds": 0,
   "idx": 9,
   "ignore_user_permissions": 0,
   "ignore_xss_filter": 0,
   "in_global_search": 0,
   "in_list_view": 0,
   "in_preview": 0,
   "in_standard_filter": 0,
   "insert_after": "is_nil_exempt",
   "label": "Is Non GST",
   "length": 0,
   "mandatory_depends_on": null,
   "modified": "2021-04-26 11:26:50.650860",
   "modified_by": "Administrator",
   "name": "Quotation Item-is_non_gst",
   "no_copy": 0,
   "non_negative": 0,
   "options": null,
   "owner": "Administrator",
   "parent": null,
   "parentfield": null,
   "parenttype": null,
   "permlevel": 0,
   "precision": "",
   "print_hide": 1,
   "print_hide_if_no_value": 0,
   "print_width": null,
   "read_only": 0,
   "read_only_depends_on": null,
   "report_hide": 0,
   "reqd": 0,
   "search_index": 0,
   "translatable": 0,
   "unique": 0,
   "width": null
  },
  {
   "_assign": null,
   "_comments": null,
   "_liked_by": null,
   "_user_tags": null,
   "allow_in_quick_entry": 0,
   "allow_on_submit": 0,
   "bold": 0,
   "collapsible": 0,
   "collapsible_depends_on": null,
   "columns": 0,
   "creation": "2021-10-30 11:37:05.839935",
   "default": null,
   "depends_on": null,
   "description": null,
   "docstatus": 0,
   "dt": "Quotation Item",
   "fetch_from": null,
   "fetch_if_empty": 0,
   "fieldname": "details",
   "fieldtype": "Section Break",
   "hidden": 0,
   "hide_border": 0,
   "hide_days": 0,
   "hide_seconds": 0,
   "idx": 74,
   "ignore_user_permissions": 0,
   "ignore_xss_filter": 0,
   "in_global_search": 0,
   "in_list_view": 0,
   "in_preview": 0,
   "in_standard_filter": 0,
   "insert_after": "page_break",
   "label": "Details",
   "length": 0,
   "mandatory_depends_on": null,
   "modified": "2021-10-30 11:37:05.839935",
   "modified_by": "Administrator",
   "name": "Quotation Item-details",
   "no_copy": 0,
   "non_negative": 0,
   "options": null,
   "owner": "Administrator",
   "parent": null,
   "parentfield": null,
   "parenttype": null,
   "permlevel": 0,
   "precision": "",
   "print_hide": 0,
   "print_hide_if_no_value": 0,
   "print_width": null,
   "read_only": 0,
   "read_only_depends_on": null,
   "report_hide": 0,
   "reqd": 0,
   "search_index": 0,
   "translatable": 0,
   "unique": 0,
   "width": null
  },
  {
   "_assign": null,
   "_comments": null,
   "_liked_by": null,
   "_user_tags": null,
   "allow_in_quick_entry": 0,
   "allow_on_submit": 0,
   "bold": 0,
   "collapsible": 0,
   "collapsible_depends_on": null,
   "columns": 0,
   "creation": "2021-10-30 11:37:06.388461",
   "default": null,
   "depends_on": null,
   "description": null,
   "docstatus": 0,
   "dt": "Quotation Item",
   "fetch_from": "item_code.fan_type",
   "fetch_if_empty": 0,
   "fieldname": "fan_type",
   "fieldtype": "Data",
   "hidden": 0,
   "hide_border": 0,
   "hide_days": 0,
   "hide_seconds": 0,
   "idx": 78,
   "ignore_user_permissions": 0,
   "ignore_xss_filter": 0,
   "in_global_search": 0,
   "in_list_view": 0,
   "in_preview": 0,
   "in_standard_filter": 0,
   "insert_after": "static_pr",
   "label": "Fan Type",
   "length": 0,
   "mandatory_depends_on": null,
   "modified": "2021-10-30 11:37:06.388461",
   "modified_by": "Administrator",
   "name": "Quotation Item-fan_type",
   "no_copy": 0,
   "non_negative": 0,
   "options": null,
   "owner": "Administrator",
   "parent": null,
   "parentfield": null,
   "parenttype": null,
   "permlevel": 0,
   "precision": "",
   "print_hide": 0,
   "print_hide_if_no_value": 0,
   "print_width": null,
   "read_only": 0,
   "read_only_depends_on": null,
   "report_hide": 0,
   "reqd": 0,
   "search_index": 0,
   "translatable": 0,
   "unique": 0,
   "width": null
  },
  {
   "_assign": null,
   "_comments": null,
   "_liked_by": null,
   "_user_tags": null,
   "allow_in_quick_entry": 0,
   "allow_on_submit": 0,
   "bold": 0,
   "collapsible": 0,
   "collapsible_depends_on": null,
   "columns": 0,
   "creation": "2021-10-30 11:37:06.548342",
   "default": null,
   "depends_on": null,
   "description": null,
   "docstatus": 0,
   "dt": "Quotation Item",
   "fetch_from": "item_code.fan_model",
   "fetch_if_empty": 0,
   "fieldname": "fan_model",
   "fieldtype": "Data",
   "hidden": 0,
   "hide_border": 0,
   "hide_days": 0,
   "hide_seconds": 0,
   "idx": 79,
   "ignore_user_permissions": 0,
   "ignore_xss_filter": 0,
   "in_global_search": 0,
   "in_list_view": 0,
   "in_preview": 0,
   "in_standard_filter": 0,
   "insert_after": "fan_type",
   "label": "Fan Model",
   "length": 0,
   "mandatory_depends_on": null,
   "modified": "2021-10-30 11:37:06.548342",
   "modified_by": "Administrator",
   "name": "Quotation Item-fan_model",
   "no_copy": 0,
   "non_negative": 0,
   "options": null,
   "owner": "Administrator",
   "parent": null,
   "parentfield": null,
   "parenttype": null,
   "permlevel": 0,
   "precision": "",
   "print_hide": 0,
   "print_hide_if_no_value": 0,
   "print_width": null,
   "read_only": 0,
   "read_only_depends_on": null,
   "report_hide": 0,
   "reqd": 0,
   "search_index": 0,
   "translatable": 0,
   "unique": 0,
   "width": null
  },
  {
   "_assign": null,
   "_comments": null,
   "_liked_by": null,
   "_user_tags": null,
   "allow_in_quick_entry": 0,
   "allow_on_submit": 0,
   "bold": 0,
   "collapsible": 0,
   "collapsible_depends_on": null,
   "columns": 0,
   "creation": "2021-10-30 11:37:06.767578",
   "default": null,
   "depends_on": null,
   "description": null,
   "docstatus": 0,
   "dt": "Quotation Item",
   "fetch_from": "item_code.fan_dia",
   "fetch_if_empty": 0,
   "fieldname": "fan_dia_",
   "fieldtype": "Float",
   "hidden": 0,
   "hide_border": 0,
   "hide_days": 0,
   "hide_seconds": 0,
   "idx": 80,
   "ignore_user_permissions": 0,
   "ignore_xss_filter": 0,
   "in_global_search": 0,
   "in_list_view": 0,
   "in_preview": 0,
   "in_standard_filter": 0,
   "insert_after": "fan_model",
   "label": "Fan Dia",
   "length": 0,
   "mandatory_depends_on": null,
   "modified": "2021-10-30 11:37:06.767578",
   "modified_by": "Administrator",
   "name": "Quotation Item-fan_dia_",
   "no_copy": 0,
   "non_negative": 0,
   "options": null,
   "owner": "Administrator",
   "parent": null,
   "parentfield": null,
   "parenttype": null,
   "permlevel": 0,
   "precision": "",
   "print_hide": 0,
   "print_hide_if_no_value": 0,
   "print_width": null,
   "read_only": 0,
   "read_only_depends_on": null,
   "report_hide": 0,
   "reqd": 0,
   "search_index": 0,
   "translatable": 0,
   "unique": 0,
   "width": null
  },
  {
   "_assign": null,
   "_comments": null,
   "_liked_by": null,
   "_user_tags": null,
   "allow_in_quick_entry": 0,
   "allow_on_submit": 0,
   "bold": 0,
   "collapsible": 0,
   "collapsible_depends_on": null,
   "columns": 0,
   "creation": "2021-10-30 11:41:57.011174",
   "default": null,
   "depends_on": null,
   "description": null,
   "docstatus": 0,
   "dt": "Quotation Item",
   "fetch_from": "item_code.kw",
   "fetch_if_empty": 0,
   "fieldname": "motor_kw",
   "fieldtype": "Float",
   "hidden": 0,
   "hide_border": 0,
   "hide_days": 0,
   "hide_seconds": 0,
   "idx": 88,
   "ignore_user_permissions": 0,
   "ignore_xss_filter": 0,
   "in_global_search": 0,
   "in_list_view": 0,
   "in_preview": 0,
   "in_standard_filter": 0,
   "insert_after": "column_break_80",
   "label": "Motor KW",
   "length": 0,
   "mandatory_depends_on": null,
   "modified": "2021-10-30 11:41:57.011174",
   "modified_by": "Administrator",
   "name": "Quotation Item-motor_kw",
   "no_copy": 0,
   "non_negative": 0,
   "options": null,
   "owner": "Administrator",
   "parent": null,
   "parentfield": null,
   "parenttype": null,
   "permlevel": 0,
   "precision": "",
   "print_hide": 0,
   "print_hide_if_no_value": 0,
   "print_width": null,
   "read_only": 0,
   "read_only_depends_on": null,
   "report_hide": 0,
   "reqd": 0,
   "search_index": 0,
   "translatable": 0,
   "unique": 0,
   "width": null
  },
  {
   "_assign": null,
   "_comments": null,
   "_liked_by": null,
   "_user_tags": null,
   "allow_in_quick_entry": 0,
   "allow_on_submit": 0,
   "bold": 0,
   "collapsible": 0,
   "collapsible_depends_on": null,
   "columns": 0,
   "creation": "2021-10-30 11:43:31.874427",
   "default": null,
   "depends_on": null,
   "description": null,
   "docstatus": 0,
   "dt": "Quotation Item",
   "fetch_from": "item_code.motor_rpm",
   "fetch_if_empty": 0,
   "fieldname": "motor_rpm",
   "fieldtype": "Data",
   "hidden": 0,
   "hide_border": 0,
   "hide_days": 0,
   "hide_seconds": 0,
   "idx": 90,
   "ignore_user_permissions": 0,
   "ignore_xss_filter": 0,
   "in_global_search": 0,
   "in_list_view": 0,
   "in_preview": 0,
   "in_standard_filter": 0,
   "insert_after": "pole",
   "label": "Motor RPM",
   "length": 0,
   "mandatory_depends_on": null,
   "modified": "2021-10-30 11:43:31.874427",
   "modified_by": "Administrator",
   "name": "Quotation Item-motor_rpm",
   "no_copy": 0,
   "non_negative": 0,
   "options": null,
   "owner": "Administrator",
   "parent": null,
   "parentfield": null,
   "parenttype": null,
   "permlevel": 0,
   "precision": "",
   "print_hide": 0,
   "print_hide_if_no_value": 0,
   "print_width": null,
   "read_only": 0,
   "read_only_depends_on": null,
   "report_hide": 0,
   "reqd": 0,
   "search_index": 0,
   "translatable": 0,
   "unique": 0,
   "width": null
  },
  {
   "_assign": null,
   "_comments": null,
   "_liked_by": null,
   "_user_tags": null,
   "allow_in_quick_entry": 0,
   "allow_on_submit": 0,
   "bold": 0,
   "collapsible": 0,
   "collapsible_depends_on": null,
   "columns": 0,
   "creation": "2021-10-30 11:43:32.199527",
   "default": null,
   "depends_on": null,
   "description": null,
   "docstatus": 0,
   "dt": "Quotation Item",
   "fetch_from": "item_code.mounting",
   "fetch_if_empty": 0,
   "fieldname": "mounting",
   "fieldtype": "Data",
   "hidden": 0,
   "hide_border": 0,
   "hide_days": 0,
   "hide_seconds": 0,
   "idx": 92,
   "ignore_user_permissions": 0,
   "ignore_xss_filter": 0,
   "in_global_search": 0,
   "in_list_view": 0,
   "in_preview": 0,
   "in_standard_filter": 0,
   "insert_after": "impeller_blade",
   "label": " Mounting",
   "length": 0,
   "mandatory_depends_on": null,
   "modified": "2021-10-30 11:43:32.199527",
   "modified_by": "Administrator",
   "name": "Quotation Item-mounting",
   "no_copy": 0,
   "non_negative": 0,
   "options": null,
   "owner": "Administrator",
   "parent": null,
   "parentfield": null,
   "parenttype": null,
   "permlevel": 0,
   "precision": "",
   "print_hide": 0,
   "print_hide_if_no_value": 0,
   "print_width": null,
   "read_only": 0,
   "read_only_depends_on": null,
   "report_hide": 0,
   "reqd": 0,
   "search_index": 0,
   "translatable": 0,
   "unique": 0,
   "width": null
  },
  {
   "_assign": null,
   "_comments": null,
   "_liked_by": null,
   "_user_tags": null,
   "allow_in_quick_entry": 0,
   "allow_on_submit": 0,
   "bold": 0,
   "collapsible": 0,
   "collapsible_depends_on": null,
   "columns": 0,
   "creation": "2021-10-30 11:43:32.498267",
   "default": null,
   "depends_on": null,
   "description": null,
   "docstatus": 0,
   "dt": "Quotation Item",
   "fetch_from": "item_code.insulation",
   "fetch_if_empty": 0,
   "fieldname": "insulation",
   "fieldtype": "Data",
   "hidden": 0,
   "hide_border": 0,
   "hide_days": 0,
   "hide_seconds": 0,
   "idx": 98,
   "ignore_user_permissions": 0,
   "ignore_xss_filter": 0,
   "in_global_search": 0,
   "in_list_view": 0,
   "in_preview": 0,
   "in_standard_filter": 0,
   "insert_after": "noise_level_after_sa_3mtr",
   "label": "Insulation",
   "length": 0,
   "mandatory_depends_on": null,
   "modified": "2021-10-30 11:43:32.498267",
   "modified_by": "Administrator",
   "name": "Quotation Item-insulation",
   "no_copy": 0,
   "non_negative": 0,
   "options": null,
   "owner": "Administrator",
   "parent": null,
   "parentfield": null,
   "parenttype": null,
   "permlevel": 0,
   "precision": "",
   "print_hide": 0,
   "print_hide_if_no_value": 0,
   "print_width": null,
   "read_only": 0,
   "read_only_depends_on": null,
   "report_hide": 0,
   "reqd": 0,
   "search_index": 0,
   "translatable": 0,
   "unique": 0,
   "width": null
  },
  {
   "_assign": null,
   "_comments": null,
   "_liked_by": null,
   "_user_tags": null,
   "allow_in_quick_entry": 0,
   "allow_on_submit": 0,
   "bold": 0,
   "collapsible": 0,
   "collapsible_depends_on": null,
   "columns": 0,
   "creation": "2021-10-30 11:48:12.618787",
   "default": null,
   "depends_on": null,
   "description": null,
   "docstatus": 0,
   "dt": "Quotation Item",
   "fetch_from": null,
   "fetch_if_empty": 0,
   "fieldname": "fan_qty",
   "fieldtype": "Float",
   "hidden": 0,
   "hide_border": 0,
   "hide_days": 0,
   "hide_seconds": 0,
   "idx": 83,
   "ignore_user_permissions": 0,
   "ignore_xss_filter": 0,
   "in_global_search": 0,
   "in_list_view": 0,
   "in_preview": 0,
   "in_standard_filter": 0,
   "insert_after": "o_v_m_s",
   "label": "Fan Qty",
   "length": 0,
   "mandatory_depends_on": null,
   "modified": "2021-10-30 11:48:12.618787",
   "modified_by": "Administrator",
   "name": "Quotation Item-fan_qty",
   "no_copy": 0,
   "non_negative": 0,
   "options": null,
   "owner": "Administrator",
   "parent": null,
   "parentfield": null,
   "parenttype": null,
   "permlevel": 0,
   "precision": "",
   "print_hide": 0,
   "print_hide_if_no_value": 0,
   "print_width": null,
   "read_only": 0,
   "read_only_depends_on": null,
   "report_hide": 0,
   "reqd": 0,
   "search_index": 0,
   "translatable": 0,
   "unique": 0,
   "width": null
  },
  {
   "_assign": null,
   "_comments": null,
   "_liked_by": null,
   "_user_tags": null,
   "allow_in_quick_entry": 0,
   "allow_on_submit": 0,
   "bold": 0,
   "collapsible": 0,
   "collapsible_depends_on": null,
   "columns": 0,
   "creation": "2021-10-30 11:52:35.091163",
   "default": null,
   "depends_on": null,
   "description": null,
   "docstatus": 0,
   "dt": "Quotation Item",
   "fetch_from": null,
   "fetch_if_empty": 0,
   "fieldname": "column_break_80",
   "fieldtype": "Column Break",
   "hidden": 0,
   "hide_border": 0,
   "hide_days": 0,
   "hide_seconds": 0,
   "idx": 87,
   "ignore_user_permissions": 0,
   "ignore_xss_filter": 0,
   "in_global_search": 0,
   "in_list_view": 0,
   "in_preview": 0,
   "in_standard_filter": 0,
   "insert_after": "no__of_blades",
   "label": "",
   "length": 0,
   "mandatory_depends_on": null,
   "modified": "2021-10-30 11:52:35.091163",
   "modified_by": "Administrator",
   "name": "Quotation Item-column_break_80",
   "no_copy": 0,
   "non_negative": 0,
   "options": null,
   "owner": "Administrator",
   "parent": null,
   "parentfield": null,
   "parenttype": null,
   "permlevel": 0,
   "precision": "",
   "print_hide": 0,
   "print_hide_if_no_value": 0,
   "print_width": null,
   "read_only": 0,
   "read_only_depends_on": null,
   "report_hide": 0,
   "reqd": 0,
   "search_index": 0,
   "translatable": 0,
   "unique": 0,
   "width": null
  },
  {
   "_assign": null,
   "_comments": null,
   "_liked_by": null,
   "_user_tags": null,
   "allow_in_quick_entry": 0,
   "allow_on_submit": 0,
   "bold": 0,
   "collapsible": 0,
   "collapsible_depends_on": null,
   "columns": 0,
   "creation": "2021-10-30 11:56:09.465994",
   "default": null,
   "depends_on": null,
   "description": null,
   "docstatus": 0,
   "dt": "Quotation Item",
   "fetch_from": null,
   "fetch_if_empty": 0,
   "fieldname": "fan_bkw",
   "fieldtype": "Data",
   "hidden": 0,
   "hide_border": 0,
   "hide_days": 0,
   "hide_seconds": 0,
   "idx": 84,
   "ignore_user_permissions": 0,
   "ignore_xss_filter": 0,
   "in_global_search": 0,
   "in_list_view": 0,
   "in_preview": 0,
   "in_standard_filter": 0,
   "insert_after": "fan_qty",
   "label": "Fan BKW",
   "length": 0,
   "mandatory_depends_on": null,
   "modified": "2021-10-30 11:56:09.465994",
   "modified_by": "Administrator",
   "name": "Quotation Item-fan_bkw",
   "no_copy": 0,
   "non_negative": 0,
   "options": null,
   "owner": "Administrator",
   "parent": null,
   "parentfield": null,
   "parenttype": null,
   "permlevel": 0,
   "precision": "",
   "print_hide": 0,
   "print_hide_if_no_value": 0,
   "print_width": null,
   "read_only": 0,
   "read_only_depends_on": null,
   "report_hide": 0,
   "reqd": 0,
   "search_index": 0,
   "translatable": 1,
   "unique": 0,
   "width": null
  },
  {
   "_assign": null,
   "_comments": null,
   "_liked_by": null,
   "_user_tags": null,
   "allow_in_quick_entry": 0,
   "allow_on_submit": 0,
   "bold": 0,
   "collapsible": 0,
   "collapsible_depends_on": null,
   "columns": 0,
   "creation": "2021-10-30 12:19:27.015519",
   "default": null,
   "depends_on": null,
   "description": null,
   "docstatus": 0,
   "dt": "Quotation Item",
   "fetch_from": null,
   "fetch_if_empty": 0,
   "fieldname": "column_break_87",
   "fieldtype": "Column Break",
   "hidden": 0,
   "hide_border": 0,
   "hide_days": 0,
   "hide_seconds": 0,
   "idx": 99,
   "ignore_user_permissions": 0,
   "ignore_xss_filter": 0,
   "in_global_search": 0,
   "in_list_view": 0,
   "in_preview": 0,
   "in_standard_filter": 0,
   "insert_after": "insulation",
   "label": null,
   "length": 0,
   "mandatory_depends_on": null,
   "modified": "2021-10-30 12:19:27.015519",
   "modified_by": "Administrator",
   "name": "Quotation Item-column_break_87",
   "no_copy": 0,
   "non_negative": 0,
   "options": null,
   "owner": "Administrator",
   "parent": null,
   "parentfield": null,
   "parenttype": null,
   "permlevel": 0,
   "precision": "",
   "print_hide": 0,
   "print_hide_if_no_value": 0,
   "print_width": null,
   "read_only": 0,
   "read_only_depends_on": null,
   "report_hide": 0,
   "reqd": 0,
   "search_index": 0,
   "translatable": 0,
   "unique": 0,
   "width": null
  },
  {
   "_assign": null,
   "_comments": null,
   "_liked_by": null,
   "_user_tags": null,
   "allow_in_quick_entry": 0,
   "allow_on_submit": 0,
   "bold": 0,
   "collapsible": 0,
   "collapsible_depends_on": null,
   "columns": 0,
   "creation": "2021-10-30 12:19:27.328279",
   "default": null,
   "depends_on": null,
   "description": null,
   "docstatus": 0,
   "dt": "Quotation Item",
   "fetch_from": "item_code.length",
   "fetch_if_empty": 0,
   "fieldname": "fan_length",
   "fieldtype": "Float",
   "hidden": 0,
   "hide_border": 0,
   "hide_days": 0,
   "hide_seconds": 0,
   "idx": 102,
   "ignore_user_permissions": 0,
   "ignore_xss_filter": 0,
   "in_global_search": 0,
   "in_list_view": 0,
   "in_preview": 0,
   "in_standard_filter": 0,
   "insert_after": "blade_angle",
   "label": "Fan Length",
   "length": 0,
   "mandatory_depends_on": null,
   "modified": "2021-10-30 12:19:27.328279",
   "modified_by": "Administrator",
   "name": "Quotation Item-fan_length",
   "no_copy": 0,
   "non_negative": 0,
   "options": null,
   "owner": "Administrator",
   "parent": null,
   "parentfield": null,
   "parenttype": null,
   "permlevel": 0,
   "precision": "",
   "print_hide": 0,
   "print_hide_if_no_value": 0,
   "print_width": null,
   "read_only": 0,
   "read_only_depends_on": null,
   "report_hide": 0,
   "reqd": 0,
   "search_index": 0,
   "translatable": 0,
   "unique": 0,
   "width": null
  },
  {
   "_assign": null,
   "_comments": null,
   "_liked_by": null,
   "_user_tags": null,
   "allow_in_quick_entry": 0,
   "allow_on_submit": 0,
   "bold": 0,
   "collapsible": 0,
   "collapsible_depends_on": null,
   "columns": 0,
   "creation": "2021-10-30 12:19:27.494059",
   "default": null,
   "depends_on": null,
   "description": null,
   "docstatus": 0,
   "dt": "Quotation Item",
   "fetch_from": "item_code.width",
   "fetch_if_empty": 0,
   "fieldname": "fan_weight",
   "fieldtype": "Float",
   "hidden": 0,
   "hide_border": 0,
   "hide_days": 0,
   "hide_seconds": 0,
   "idx": 103,
   "ignore_user_permissions": 0,
   "ignore_xss_filter": 0,
   "in_global_search": 0,
   "in_list_view": 0,
   "in_preview": 0,
   "in_standard_filter": 0,
   "insert_after": "fan_length",
   "label": "Fan Width",
   "length": 0,
   "mandatory_depends_on": null,
   "modified": "2021-10-30 12:19:27.494059",
   "modified_by": "Administrator",
   "name": "Quotation Item-fan_weight",
   "no_copy": 0,
   "non_negative": 0,
   "options": null,
   "owner": "Administrator",
   "parent": null,
   "parentfield": null,
   "parenttype": null,
   "permlevel": 0,
   "precision": "",
   "print_hide": 0,
   "print_hide_if_no_value": 0,
   "print_width": null,
   "read_only": 0,
   "read_only_depends_on": null,
   "report_hide": 0,
   "reqd": 0,
   "search_index": 0,
   "translatable": 0,
   "unique": 0,
   "width": null
  },
  {
   "_assign": null,
   "_comments": null,
   "_liked_by": null,
   "_user_tags": null,
   "allow_in_quick_entry": 0,
   "allow_on_submit": 0,
   "bold": 0,
   "collapsible": 0,
   "collapsible_depends_on": null,
   "columns": 0,
   "creation": "2021-10-30 12:19:27.653577",
   "default": null,
   "depends_on": null,
   "description": null,
   "docstatus": 0,
   "dt": "Quotation Item",
   "fetch_from": "item_code.area",
   "fetch_if_empty": 0,
   "fieldname": "area",
   "fieldtype": "Float",
   "hidden": 0,
   "hide_border": 0,
   "hide_days": 0,
   "hide_seconds": 0,
   "idx": 105,
   "ignore_user_permissions": 0,
   "ignore_xss_filter": 0,
   "in_global_search": 0,
   "in_list_view": 0,
   "in_preview": 0,
   "in_standard_filter": 0,
   "insert_after": "fa_height",
   "label": "Area",
   "length": 0,
   "mandatory_depends_on": null,
   "modified": "2021-10-30 12:19:27.653577",
   "modified_by": "Administrator",
   "name": "Quotation Item-area",
   "no_copy": 0,
   "non_negative": 0,
   "options": null,
   "owner": "Administrator",
   "parent": null,
   "parentfield": null,
   "parenttype": null,
   "permlevel": 0,
   "precision": "",
   "print_hide": 0,
   "print_hide_if_no_value": 0,
   "print_width": null,
   "read_only": 0,
   "read_only_depends_on": null,
   "report_hide": 0,
   "reqd": 0,
   "search_index": 0,
   "translatable": 0,
   "unique": 0,
   "width": null
  },
  {
   "_assign": null,
   "_comments": null,
   "_liked_by": null,
   "_user_tags": null,
   "allow_in_quick_entry": 0,
   "allow_on_submit": 0,
   "bold": 0,
   "collapsible": 0,
   "collapsible_depends_on": null,
   "columns": 0,
   "creation": "2021-10-30 12:25:39.641120",
   "default": null,
   "depends_on": null,
   "description": null,
   "docstatus": 0,
   "dt": "Quotation Item",
   "fetch_from": null,
   "fetch_if_empty": 0,
   "fieldname": "blade_angle",
   "fieldtype": "Float",
   "hidden": 0,
   "hide_border": 0,
   "hide_days": 0,
   "hide_seconds": 0,
   "idx": 101,
   "ignore_user_permissions": 0,
   "ignore_xss_filter": 0,
   "in_global_search": 0,
   "in_list_view": 0,
   "in_preview": 0,
   "in_standard_filter": 0,
   "insert_after": "class",
   "label": "Blade Angle",
   "length": 0,
   "mandatory_depends_on": null,
   "modified": "2021-10-30 12:25:39.641120",
   "modified_by": "Administrator",
   "name": "Quotation Item-blade_angle",
   "no_copy": 0,
   "non_negative": 0,
   "options": null,
   "owner": "Administrator",
   "parent": null,
   "parentfield": null,
   "parenttype": null,
   "permlevel": 0,
   "precision": "",
   "print_hide": 0,
   "print_hide_if_no_value": 0,
   "print_width": null,
   "read_only": 0,
   "read_only_depends_on": null,
   "report_hide": 0,
   "reqd": 0,
   "search_index": 0,
   "translatable": 0,
   "unique": 0,
   "width": null
  },
  {
   "_assign": null,
   "_comments": null,
   "_liked_by": null,
   "_user_tags": null,
   "allow_in_quick_entry": 0,
   "allow_on_submit": 0,
   "bold": 0,
   "collapsible": 0,
   "collapsible_depends_on": null,
   "columns": 0,
   "creation": "2021-10-30 12:26:35.950893",
   "default": null,
   "depends_on": null,
   "description": null,
   "docstatus": 0,
   "dt": "Quotation Item",
   "fetch_from": "item_code.pole",
   "fetch_if_empty": 0,
   "fieldname": "pole",
   "fieldtype": "Data",
   "hidden": 0,
   "hide_border": 0,
   "hide_days": 0,
   "hide_seconds": 0,
   "idx": 89,
   "ignore_user_permissions": 0,
   "ignore_xss_filter": 0,
   "in_global_search": 0,
   "in_list_view": 0,
   "in_preview": 0,
   "in_standard_filter": 0,
   "insert_after": "motor_kw",
   "label": "Pole",
   "length": 0,
   "mandatory_depends_on": null,
   "modified": "2021-10-30 12:26:35.950893",
   "modified_by": "Administrator",
   "name": "Quotation Item-pole",
   "no_copy": 0,
   "non_negative": 0,
   "options": null,
   "owner": "Administrator",
   "parent": null,
   "parentfield": null,
   "parenttype": null,
   "permlevel": 0,
   "precision": "",
   "print_hide": 0,
   "print_hide_if_no_value": 0,
   "print_width": null,
   "read_only": 0,
   "read_only_depends_on": null,
   "report_hide": 0,
   "reqd": 0,
   "search_index": 0,
   "translatable": 0,
   "unique": 0,
   "width": null
  },
  {
   "_assign": null,
   "_comments": null,
   "_liked_by": null,
   "_user_tags": null,
   "allow_in_quick_entry": 0,
   "allow_on_submit": 0,
   "bold": 0,
   "collapsible": 0,
   "collapsible_depends_on": null,
   "columns": 0,
   "creation": "2021-10-30 12:26:36.261160",
   "default": null,
   "depends_on": null,
   "description": null,
   "docstatus": 0,
   "dt": "Quotation Item",
   "fetch_from": null,
   "fetch_if_empty": 0,
   "fieldname": "impeller_blade",
   "fieldtype": "Data",
   "hidden": 0,
   "hide_border": 0,
   "hide_days": 0,
   "hide_seconds": 0,
   "idx": 91,
   "ignore_user_permissions": 0,
   "ignore_xss_filter": 0,
   "in_global_search": 0,
   "in_list_view": 0,
   "in_preview": 0,
   "in_standard_filter": 0,
   "insert_after": "motor_rpm",
   "label": "Impeller Blade",
   "length": 0,
   "mandatory_depends_on": null,
   "modified": "2021-10-30 12:26:36.261160",
   "modified_by": "Administrator",
   "name": "Quotation Item-impeller_blade",
   "no_copy": 0,
   "non_negative": 0,
   "options": null,
   "owner": "Administrator",
   "parent": null,
   "parentfield": null,
   "parenttype": null,
   "permlevel": 0,
   "precision": "",
   "print_hide": 0,
   "print_hide_if_no_value": 0,
   "print_width": null,
   "read_only": 0,
   "read_only_depends_on": null,
   "report_hide": 0,
   "reqd": 0,
   "search_index": 0,
   "translatable": 1,
   "unique": 0,
   "width": null
  },
  {
   "_assign": null,
   "_comments": null,
   "_liked_by": null,
   "_user_tags": null,
   "allow_in_quick_entry": 0,
   "allow_on_submit": 0,
   "bold": 0,
   "collapsible": 0,
   "collapsible_depends_on": null,
   "columns": 0,
   "creation": "2021-10-30 12:30:28.866823",
   "default": null,
   "depends_on": null,
   "description": null,
   "docstatus": 0,
   "dt": "Quotation Item",
   "fetch_from": "item_code.noise_source",
   "fetch_if_empty": 0,
   "fieldname": "noise__source",
   "fieldtype": "Data",
   "hidden": 0,
   "hide_border": 0,
   "hide_days": 0,
   "hide_seconds": 0,
   "idx": 93,
   "ignore_user_permissions": 0,
   "ignore_xss_filter": 0,
   "in_global_search": 0,
   "in_list_view": 0,
   "in_preview": 0,
   "in_standard_filter": 0,
   "insert_after": "mounting",
   "label": "Noise  Source",
   "length": 0,
   "mandatory_depends_on": null,
   "modified": "2021-10-30 12:30:28.866823",
   "modified_by": "Administrator",
   "name": "Quotation Item-noise__source",
   "no_copy": 0,
   "non_negative": 0,
   "options": null,
   "owner": "Administrator",
   "parent": null,
   "parentfield": null,
   "parenttype": null,
   "permlevel": 0,
   "precision": "",
   "print_hide": 0,
   "print_hide_if_no_value": 0,
   "print_width": null,
   "read_only": 0,
   "read_only_depends_on": null,
   "report_hide": 0,
   "reqd": 0,
   "search_index": 0,
   "translatable": 0,
   "unique": 0,
   "width": null
  },
  {
   "_assign": null,
   "_comments": null,
   "_liked_by": null,
   "_user_tags": null,
   "allow_in_quick_entry": 0,
   "allow_on_submit": 0,
   "bold": 0,
   "collapsible": 0,
   "collapsible_depends_on": null,
   "columns": 0,
   "creation": "2021-10-30 12:31:29.929405",
   "default": null,
   "depends_on": null,
   "description": null,
   "docstatus": 0,
   "dt": "Quotation Item",
   "fetch_from": null,
   "fetch_if_empty": 0,
   "fieldname": "noise_level_1mtr",
   "fieldtype": "Data",
   "hidden": 0,
   "hide_border": 0,
   "hide_days": 0,
   "hide_seconds": 0,
   "idx": 94,
   "ignore_user_permissions": 0,
   "ignore_xss_filter": 0,
   "in_global_search": 0,
   "in_list_view": 0,
   "in_preview": 0,
   "in_standard_filter": 0,
   "insert_after": "noise__source",
   "label": "Noise Level 1Mtr",
   "length": 0,
   "mandatory_depends_on": null,
   "modified": "2021-10-30 12:31:29.929405",
   "modified_by": "Administrator",
   "name": "Quotation Item-noise_level_1mtr",
   "no_copy": 0,
   "non_negative": 0,
   "options": null,
   "owner": "Administrator",
   "parent": null,
   "parentfield": null,
   "parenttype": null,
   "permlevel": 0,
   "precision": "",
   "print_hide": 0,
   "print_hide_if_no_value": 0,
   "print_width": null,
   "read_only": 0,
   "read_only_depends_on": null,
   "report_hide": 0,
   "reqd": 0,
   "search_index": 0,
   "translatable": 1,
   "unique": 0,
   "width": null
  },
  {
   "_assign": null,
   "_comments": null,
   "_liked_by": null,
   "_user_tags": null,
   "allow_in_quick_entry": 0,
   "allow_on_submit": 0,
   "bold": 0,
   "collapsible": 0,
   "collapsible_depends_on": null,
   "columns": 0,
   "creation": "2021-10-30 12:31:30.125603",
   "default": null,
   "depends_on": null,
   "description": null,
   "docstatus": 0,
   "dt": "Quotation Item",
   "fetch_from": null,
   "fetch_if_empty": 0,
   "fieldname": "noise_level_2mtr",
   "fieldtype": "Data",
   "hidden": 0,
   "hide_border": 0,
   "hide_days": 0,
   "hide_seconds": 0,
   "idx": 95,
   "ignore_user_permissions": 0,
   "ignore_xss_filter": 0,
   "in_global_search": 0,
   "in_list_view": 0,
   "in_preview": 0,
   "in_standard_filter": 0,
   "insert_after": "noise_level_1mtr",
   "label": "Noise Level 2Mtr",
   "length": 0,
   "mandatory_depends_on": null,
   "modified": "2021-10-30 12:31:30.125603",
   "modified_by": "Administrator",
   "name": "Quotation Item-noise_level_2mtr",
   "no_copy": 0,
   "non_negative": 0,
   "options": null,
   "owner": "Administrator",
   "parent": null,
   "parentfield": null,
   "parenttype": null,
   "permlevel": 0,
   "precision": "",
   "print_hide": 0,
   "print_hide_if_no_value": 0,
   "print_width": null,
   "read_only": 0,
   "read_only_depends_on": null,
   "report_hide": 0,
   "reqd": 0,
   "search_index": 0,
   "translatable": 1,
   "unique": 0,
   "width": null
  },
  {
   "_assign": null,
   "_comments": null,
   "_liked_by": null,
   "_user_tags": null,
   "allow_in_quick_entry": 0,
   "allow_on_submit": 0,
   "bold": 0,
   "collapsible": 0,
   "collapsible_depends_on": null,
   "columns": 0,
   "creation": "2021-10-30 12:31:30.342027",
   "default": null,
   "depends_on": null,
   "description": null,
   "docstatus": 0,
   "dt": "Quotation Item",
   "fetch_from": null,
   "fetch_if_empty": 0,
   "fieldname": "noise_level_after_sa_3mtr",
   "fieldtype": "Data",
   "hidden": 0,
   "hide_border": 0,
   "hide_days": 0,
   "hide_seconds": 0,
   "idx": 97,
   "ignore_user_permissions": 0,
   "ignore_xss_filter": 0,
   "in_global_search": 0,
   "in_list_view": 0,
   "in_preview": 0,
   "in_standard_filter": 0,
   "insert_after": "noise_level_3mtr",
   "label": "Noise Level after SA 3Mtr",
   "length": 0,
   "mandatory_depends_on": null,
   "modified": "2021-10-30 12:31:30.342027",
   "modified_by": "Administrator",
   "name": "Quotation Item-noise_level_after_sa_3mtr",
   "no_copy": 0,
   "non_negative": 0,
   "options": null,
   "owner": "Administrator",
   "parent": null,
   "parentfield": null,
   "parenttype": null,
   "permlevel": 0,
   "precision": "",
   "print_hide": 0,
   "print_hide_if_no_value": 0,
   "print_width": null,
   "read_only": 0,
   "read_only_depends_on": null,
   "report_hide": 0,
   "reqd": 0,
   "search_index": 0,
   "translatable": 1,
   "unique": 0,
   "width": null
  },
  {
   "_assign": null,
   "_comments": null,
   "_liked_by": null,
   "_user_tags": null,
   "allow_in_quick_entry": 0,
   "allow_on_submit": 0,
   "bold": 0,
   "collapsible": 0,
   "collapsible_depends_on": null,
   "columns": 0,
   "creation": "2021-10-30 12:43:49.873313",
   "default": null,
   "depends_on": null,
   "description": null,
   "docstatus": 0,
   "dt": "Quotation Item",
   "fetch_from": "item_code.class",
   "fetch_if_empty": 0,
   "fieldname": "class",
   "fieldtype": "Data",
   "hidden": 0,
   "hide_border": 0,
   "hide_days": 0,
   "hide_seconds": 0,
   "idx": 100,
   "ignore_user_permissions": 0,
   "ignore_xss_filter": 0,
   "in_global_search": 0,
   "in_list_view": 0,
   "in_preview": 0,
   "in_standard_filter": 0,
   "insert_after": "column_break_87",
   "label": "Class",
   "length": 0,
   "mandatory_depends_on": null,
   "modified": "2021-10-30 12:43:49.873313",
   "modified_by": "Administrator",
   "name": "Quotation Item-class",
   "no_copy": 0,
   "non_negative": 0,
   "options": null,
   "owner": "Administrator",
   "parent": null,
   "parentfield": null,
   "parenttype": null,
   "permlevel": 0,
   "precision": "",
   "print_hide": 0,
   "print_hide_if_no_value": 0,
   "print_width": null,
   "read_only": 0,
   "read_only_depends_on": null,
   "report_hide": 0,
   "reqd": 0,
   "search_index": 0,
   "translatable": 0,
   "unique": 0,
   "width": null
  },
  {
   "_assign": null,
   "_comments": null,
   "_liked_by": null,
   "_user_tags": null,
   "allow_in_quick_entry": 0,
   "allow_on_submit": 0,
   "bold": 0,
   "collapsible": 0,
   "collapsible_depends_on": null,
   "columns": 0,
   "creation": "2021-10-30 12:44:39.831257",
   "default": null,
   "depends_on": null,
   "description": null,
   "docstatus": 0,
   "dt": "Quotation Item",
   "fetch_from": "item_code.height",
   "fetch_if_empty": 0,
   "fieldname": "fa_height",
   "fieldtype": "Float",
   "hidden": 0,
   "hide_border": 0,
   "hide_days": 0,
   "hide_seconds": 0,
   "idx": 104,
   "ignore_user_permissions": 0,
   "ignore_xss_filter": 0,
   "in_global_search": 0,
   "in_list_view": 0,
   "in_preview": 0,
   "in_standard_filter": 0,
   "insert_after": "fan_weight",
   "label": "Fan Height",
   "length": 0,
   "mandatory_depends_on": null,
   "modified": "2021-10-30 12:44:39.831257",
   "modified_by": "Administrator",
   "name": "Quotation Item-fa_height",
   "no_copy": 0,
   "non_negative": 0,
   "options": null,
   "owner": "Administrator",
   "parent": null,
   "parentfield": null,
   "parenttype": null,
   "permlevel": 0,
   "precision": "",
   "print_hide": 0,
   "print_hide_if_no_value": 0,
   "print_width": null,
   "read_only": 0,
   "read_only_depends_on": null,
   "report_hide": 0,
   "reqd": 0,
   "search_index": 0,
   "translatable": 0,
   "unique": 0,
   "width": null
  },
  {
   "_assign": null,
   "_comments": null,
   "_liked_by": null,
   "_user_tags": null,
   "allow_in_quick_entry": 0,
   "allow_on_submit": 0,
   "bold": 0,
   "collapsible": 0,
   "collapsible_depends_on": null,
   "columns": 0,
   "creation": "2021-10-30 13:33:53.832798",
   "default": null,
   "depends_on": null,
   "description": null,
   "docstatus": 0,
   "dt": "Quotation Item",
   "fetch_from": null,
   "fetch_if_empty": 0,
   "fieldname": "capacity_cmh",
   "fieldtype": "Data",
   "hidden": 0,
   "hide_border": 0,
   "hide_days": 0,
   "hide_seconds": 0,
   "idx": 76,
   "ignore_user_permissions": 0,
   "ignore_xss_filter": 0,
   "in_global_search": 0,
   "in_list_view": 0,
   "in_preview": 0,
   "in_standard_filter": 0,
   "insert_after": "capacity_cfm",
   "label": "Capacity CMH",
   "length": 0,
   "mandatory_depends_on": null,
   "modified": "2021-10-30 13:33:53.832798",
   "modified_by": "Administrator",
   "name": "Quotation Item-capacity_cmh",
   "no_copy": 0,
   "non_negative": 0,
   "options": null,
   "owner": "Administrator",
   "parent": null,
   "parentfield": null,
   "parenttype": null,
   "permlevel": 0,
   "precision": "",
   "print_hide": 0,
   "print_hide_if_no_value": 0,
   "print_width": null,
   "read_only": 1,
   "read_only_depends_on": null,
   "report_hide": 0,
   "reqd": 0,
   "search_index": 0,
   "translatable": 1,
   "unique": 0,
   "width": null
  },
  {
   "_assign": null,
   "_comments": null,
   "_liked_by": null,
   "_user_tags": null,
   "allow_in_quick_entry": 0,
   "allow_on_submit": 0,
   "bold": 0,
   "collapsible": 0,
   "collapsible_depends_on": null,
   "columns": 0,
   "creation": "2021-10-30 13:35:20.080450",
   "default": null,
   "depends_on": null,
   "description": null,
   "docstatus": 0,
   "dt": "Quotation Item",
   "fetch_from": null,
   "fetch_if_empty": 0,
   "fieldname": "capacity_cfm",
   "fieldtype": "Data",
   "hidden": 0,
   "hide_border": 0,
   "hide_days": 0,
   "hide_seconds": 0,
   "idx": 75,
   "ignore_user_permissions": 0,
   "ignore_xss_filter": 0,
   "in_global_search": 0,
   "in_list_view": 0,
   "in_preview": 0,
   "in_standard_filter": 0,
   "insert_after": "details",
   "label": "Capacity CFM",
   "length": 0,
   "mandatory_depends_on": null,
   "modified": "2021-10-30 13:35:20.080450",
   "modified_by": "Administrator",
   "name": "Quotation Item-capacity_cfm",
   "no_copy": 0,
   "non_negative": 0,
   "options": null,
   "owner": "Administrator",
   "parent": null,
   "parentfield": null,
   "parenttype": null,
   "permlevel": 0,
   "precision": "",
   "print_hide": 0,
   "print_hide_if_no_value": 0,
   "print_width": null,
   "read_only": 0,
   "read_only_depends_on": null,
   "report_hide": 0,
   "reqd": 0,
   "search_index": 0,
   "translatable": 1,
   "unique": 0,
   "width": null
  },
  {
   "_assign": null,
   "_comments": null,
   "_liked_by": null,
   "_user_tags": null,
   "allow_in_quick_entry": 0,
   "allow_on_submit": 0,
   "bold": 0,
   "collapsible": 0,
   "collapsible_depends_on": null,
   "columns": 0,
   "creation": "2021-10-30 14:19:38.302316",
   "default": null,
   "depends_on": "",
   "description": null,
   "docstatus": 0,
   "dt": "Quotation Item",
   "fetch_from": null,
   "fetch_if_empty": 0,
   "fieldname": "o_v_m_s",
   "fieldtype": "Data",
   "hidden": 0,
   "hide_border": 0,
   "hide_days": 0,
   "hide_seconds": 0,
   "idx": 82,
   "ignore_user_permissions": 0,
   "ignore_xss_filter": 0,
   "in_global_search": 0,
   "in_list_view": 0,
   "in_preview": 0,
   "in_standard_filter": 0,
   "insert_after": "outlet_area",
   "label": "O/V M/S",
   "length": 0,
   "mandatory_depends_on": null,
   "modified": "2021-10-30 14:19:38.302316",
   "modified_by": "Administrator",
   "name": "Quotation Item-o_v_m_s",
   "no_copy": 0,
   "non_negative": 0,
   "options": null,
   "owner": "Administrator",
   "parent": null,
   "parentfield": null,
   "parenttype": null,
   "permlevel": 0,
   "precision": "",
   "print_hide": 0,
   "print_hide_if_no_value": 0,
   "print_width": null,
   "read_only": 1,
   "read_only_depends_on": null,
   "report_hide": 0,
   "reqd": 0,
   "search_index": 0,
   "translatable": 1,
   "unique": 0,
   "width": null
  },
  {
   "_assign": null,
   "_comments": null,
   "_liked_by": null,
   "_user_tags": null,
   "allow_in_quick_entry": 0,
   "allow_on_submit": 0,
   "bold": 0,
   "collapsible": 0,
   "collapsible_depends_on": null,
   "columns": 0,
   "creation": "2021-10-30 14:24:26.365624",
   "default": null,
   "depends_on": null,
   "description": null,
   "docstatus": 0,
   "dt": "Quotation Item",
   "fetch_from": null,
   "fetch_if_empty": 0,
   "fieldname": "vel_pr",
   "fieldtype": "Data",
   "hidden": 0,
   "hide_border": 0,
   "hide_days": 0,
   "hide_seconds": 0,
   "idx": 106,
   "ignore_user_permissions": 0,
   "ignore_xss_filter": 0,
   "in_global_search": 0,
   "in_list_view": 0,
   "in_preview": 0,
   "in_standard_filter": 0,
   "insert_after": "area",
   "label": "Vel Pr",
   "length": 0,
   "mandatory_depends_on": null,
   "modified": "2021-10-30 14:24:26.365624",
   "modified_by": "Administrator",
   "name": "Quotation Item-vel_pr",
   "no_copy": 0,
   "non_negative": 0,
   "options": null,
   "owner": "Administrator",
   "parent": null,
   "parentfield": null,
   "parenttype": null,
   "permlevel": 0,
   "precision": "",
   "print_hide": 0,
   "print_hide_if_no_value": 0,
   "print_width": null,
   "read_only": 1,
   "read_only_depends_on": null,
   "report_hide": 0,
   "reqd": 0,
   "search_index": 0,
   "translatable": 1,
   "unique": 0,
   "width": null
  },
  {
   "_assign": null,
   "_comments": null,
   "_liked_by": null,
   "_user_tags": null,
   "allow_in_quick_entry": 0,
   "allow_on_submit": 0,
   "bold": 0,
   "collapsible": 0,
   "collapsible_depends_on": null,
   "columns": 0,
   "creation": "2021-10-30 15:37:28.880320",
   "default": null,
   "depends_on": null,
   "description": null,
   "docstatus": 0,
   "dt": "Quotation Item",
   "fetch_from": null,
   "fetch_if_empty": 0,
   "fieldname": "suggested_bkw",
   "fieldtype": "Data",
   "hidden": 0,
   "hide_border": 0,
   "hide_days": 0,
   "hide_seconds": 0,
   "idx": 107,
   "ignore_user_permissions": 0,
   "ignore_xss_filter": 0,
   "in_global_search": 0,
   "in_list_view": 0,
   "in_preview": 0,
   "in_standard_filter": 0,
   "insert_after": "vel_pr",
   "label": "Suggested BKW",
   "length": 0,
   "mandatory_depends_on": null,
   "modified": "2021-10-30 15:37:28.880320",
   "modified_by": "Administrator",
   "name": "Quotation Item-suggested_bkw",
   "no_copy": 0,
   "non_negative": 0,
   "options": null,
   "owner": "Administrator",
   "parent": null,
   "parentfield": null,
   "parenttype": null,
   "permlevel": 0,
   "precision": "",
   "print_hide": 0,
   "print_hide_if_no_value": 0,
   "print_width": null,
   "read_only": 1,
   "read_only_depends_on": null,
   "report_hide": 0,
   "reqd": 0,
   "search_index": 0,
   "translatable": 0,
   "unique": 0,
   "width": null
  },
  {
   "_assign": null,
   "_comments": null,
   "_liked_by": null,
   "_user_tags": null,
   "allow_in_quick_entry": 0,
   "allow_on_submit": 0,
   "bold": 0,
   "collapsible": 0,
   "collapsible_depends_on": null,
   "columns": 0,
   "creation": "2021-10-30 15:54:53.775855",
   "default": null,
   "depends_on": null,
   "description": null,
   "docstatus": 0,
   "dt": "Quotation Item",
   "fetch_from": null,
   "fetch_if_empty": 0,
   "fieldname": "static_pr",
   "fieldtype": "Data",
   "hidden": 0,
   "hide_border": 0,
   "hide_days": 0,
   "hide_seconds": 0,
   "idx": 77,
   "ignore_user_permissions": 0,
   "ignore_xss_filter": 0,
   "in_global_search": 0,
   "in_list_view": 0,
   "in_preview": 0,
   "in_standard_filter": 0,
   "insert_after": "capacity_cmh",
   "label": "Static Pr",
   "length": 0,
   "mandatory_depends_on": null,
   "modified": "2021-10-30 15:54:53.775855",
   "modified_by": "Administrator",
   "name": "Quotation Item-static_pr",
   "no_copy": 0,
   "non_negative": 0,
   "options": null,
   "owner": "Administrator",
   "parent": null,
   "parentfield": null,
   "parenttype": null,
   "permlevel": 0,
   "precision": "",
   "print_hide": 0,
   "print_hide_if_no_value": 0,
   "print_width": null,
   "read_only": 0,
   "read_only_depends_on": null,
   "report_hide": 0,
   "reqd": 0,
   "search_index": 0,
   "translatable": 1,
   "unique": 0,
   "width": null
  },
  {
   "_assign": null,
   "_comments": null,
   "_liked_by": null,
   "_user_tags": null,
   "allow_in_quick_entry": 0,
   "allow_on_submit": 0,
   "bold": 0,
   "collapsible": 0,
   "collapsible_depends_on": null,
   "columns": 0,
   "creation": "2021-10-30 15:58:05.417382",
   "default": null,
   "depends_on": null,
   "description": null,
   "docstatus": 0,
   "dt": "Quotation Item",
   "fetch_from": null,
   "fetch_if_empty": 0,
   "fieldname": "efficiency",
   "fieldtype": "Data",
   "hidden": 0,
   "hide_border": 0,
   "hide_days": 0,
   "hide_seconds": 0,
   "idx": 108,
   "ignore_user_permissions": 0,
   "ignore_xss_filter": 0,
   "in_global_search": 0,
   "in_list_view": 0,
   "in_preview": 0,
   "in_standard_filter": 0,
   "insert_after": "suggested_bkw",
   "label": "Efficiency",
   "length": 0,
   "mandatory_depends_on": null,
   "modified": "2021-10-30 15:58:05.417382",
   "modified_by": "Administrator",
   "name": "Quotation Item-efficiency",
   "no_copy": 0,
   "non_negative": 0,
   "options": null,
   "owner": "Administrator",
   "parent": null,
   "parentfield": null,
   "parenttype": null,
   "permlevel": 0,
   "precision": "",
   "print_hide": 0,
   "print_hide_if_no_value": 0,
   "print_width": null,
   "read_only": 1,
   "read_only_depends_on": null,
   "report_hide": 0,
   "reqd": 0,
   "search_index": 0,
   "translatable": 0,
   "unique": 0,
   "width": null
  },
  {
   "_assign": null,
   "_comments": null,
   "_liked_by": null,
   "_user_tags": null,
   "allow_in_quick_entry": 0,
   "allow_on_submit": 0,
   "bold": 0,
   "collapsible": 0,
   "collapsible_depends_on": null,
   "columns": 0,
   "creation": "2021-11-09 12:58:53.548937",
   "default": null,
   "depends_on": null,
   "description": null,
   "docstatus": 0,
   "dt": "Quotation Item",
   "fetch_from": null,
   "fetch_if_empty": 0,
   "fieldname": "noise_level_3mtr",
   "fieldtype": "Data",
   "hidden": 0,
   "hide_border": 0,
   "hide_days": 0,
   "hide_seconds": 0,
   "idx": 96,
   "ignore_user_permissions": 0,
   "ignore_xss_filter": 0,
   "in_global_search": 0,
   "in_list_view": 0,
   "in_preview": 0,
   "in_standard_filter": 0,
   "insert_after": "noise_level_2mtr",
   "label": "Noise Level 3Mtr",
   "length": 0,
   "mandatory_depends_on": null,
   "modified": "2021-11-09 12:58:53.548937",
   "modified_by": "Administrator",
   "name": "Quotation Item-noise_level_3mtr",
   "no_copy": 0,
   "non_negative": 0,
   "options": null,
   "owner": "Administrator",
   "parent": null,
   "parentfield": null,
   "parenttype": null,
   "permlevel": 0,
   "precision": "",
   "print_hide": 0,
   "print_hide_if_no_value": 0,
   "print_width": null,
   "read_only": 0,
   "read_only_depends_on": null,
   "report_hide": 0,
   "reqd": 0,
   "search_index": 0,
   "translatable": 1,
   "unique": 0,
   "width": null
  },
  {
   "_assign": null,
   "_comments": null,
   "_liked_by": null,
   "_user_tags": null,
   "allow_in_quick_entry": 0,
   "allow_on_submit": 0,
   "bold": 0,
   "collapsible": 0,
   "collapsible_depends_on": null,
   "columns": 0,
   "creation": "2021-11-09 12:59:15.336022",
   "default": null,
   "depends_on": null,
   "description": null,
   "docstatus": 0,
   "dt": "Quotation Item",
   "fetch_from": "item_code.fan_rpm",
   "fetch_if_empty": 0,
   "fieldname": "fan_rpm",
   "fieldtype": "Data",
   "hidden": 0,
   "hide_border": 0,
   "hide_days": 0,
   "hide_seconds": 0,
   "idx": 85,
   "ignore_user_permissions": 0,
   "ignore_xss_filter": 0,
   "in_global_search": 0,
   "in_list_view": 0,
   "in_preview": 0,
   "in_standard_filter": 0,
   "insert_after": "fan_bkw",
   "label": "Fan RPM",
   "length": 0,
   "mandatory_depends_on": null,
   "modified": "2021-11-09 12:59:15.336022",
   "modified_by": "Administrator",
   "name": "Quotation Item-fan_rpm",
   "no_copy": 0,
   "non_negative": 0,
   "options": null,
   "owner": "Administrator",
   "parent": null,
   "parentfield": null,
   "parenttype": null,
   "permlevel": 0,
   "precision": "",
   "print_hide": 0,
   "print_hide_if_no_value": 0,
   "print_width": null,
   "read_only": 0,
   "read_only_depends_on": null,
   "report_hide": 0,
   "reqd": 0,
   "search_index": 0,
   "translatable": 0,
   "unique": 0,
   "width": null
  },
  {
   "_assign": null,
   "_comments": null,
   "_liked_by": null,
   "_user_tags": null,
   "allow_in_quick_entry": 0,
   "allow_on_submit": 0,
   "bold": 0,
   "collapsible": 0,
   "collapsible_depends_on": null,
   "columns": 0,
   "creation": "2021-11-09 13:03:54.729001",
   "default": null,
   "depends_on": null,
   "description": null,
   "docstatus": 0,
   "dt": "Quotation Item",
   "fetch_from": null,
   "fetch_if_empty": 0,
   "fieldname": "no__of_blades",
   "fieldtype": "Data",
   "hidden": 0,
   "hide_border": 0,
   "hide_days": 0,
   "hide_seconds": 0,
   "idx": 86,
   "ignore_user_permissions": 0,
   "ignore_xss_filter": 0,
   "in_global_search": 0,
   "in_list_view": 0,
   "in_preview": 0,
   "in_standard_filter": 0,
   "insert_after": "fan_rpm",
   "label": "No of blades",
   "length": 0,
   "mandatory_depends_on": null,
   "modified": "2021-11-09 13:03:54.729001",
   "modified_by": "Administrator",
   "name": "Quotation Item-no__of_blades",
   "no_copy": 0,
   "non_negative": 0,
   "options": null,
   "owner": "Administrator",
   "parent": null,
   "parentfield": null,
   "parenttype": null,
   "permlevel": 0,
   "precision": "",
   "print_hide": 0,
   "print_hide_if_no_value": 0,
   "print_width": null,
   "read_only": 0,
   "read_only_depends_on": null,
   "report_hide": 0,
   "reqd": 0,
   "search_index": 0,
   "translatable": 1,
   "unique": 0,
   "width": null
  },
  {
   "_assign": null,
   "_comments": null,
   "_liked_by": null,
   "_user_tags": null,
   "allow_in_quick_entry": 0,
   "allow_on_submit": 0,
   "bold": 0,
   "collapsible": 0,
   "collapsible_depends_on": null,
   "columns": 0,
   "creation": "2021-11-13 12:58:13.458952",
   "default": null,
   "depends_on": "eval:doc.fan_type == \"Double Skin\"",
   "description": null,
   "docstatus": 0,
   "dt": "Quotation Item",
   "fetch_from": null,
   "fetch_if_empty": 0,
   "fieldname": "outlet_area",
   "fieldtype": "Data",
   "hidden": 0,
   "hide_border": 0,
   "hide_days": 0,
   "hide_seconds": 0,
   "idx": 81,
   "ignore_user_permissions": 0,
   "ignore_xss_filter": 0,
   "in_global_search": 0,
   "in_list_view": 0,
   "in_preview": 0,
   "in_standard_filter": 0,
   "insert_after": "fan_dia_",
   "label": "Outlet Area",
   "length": 0,
   "mandatory_depends_on": null,
   "modified": "2021-11-13 12:58:13.458952",
   "modified_by": "Administrator",
   "name": "Quotation Item-outlet_area",
   "no_copy": 0,
   "non_negative": 0,
   "options": null,
   "owner": "Administrator",
   "parent": null,
   "parentfield": null,
   "parenttype": null,
   "permlevel": 0,
   "precision": "",
   "print_hide": 0,
   "print_hide_if_no_value": 0,
   "print_width": null,
   "read_only": 0,
   "read_only_depends_on": null,
   "report_hide": 0,
   "reqd": 0,
   "search_index": 0,
   "translatable": 1,
   "unique": 0,
   "width": null
  }
 ],
 "custom_perms": [],
 "doctype": "Quotation Item",
 "property_setters": [],
 "sync_on_migrate": 1
}